LICENSE
README.rst
requirements.txt
setup.py
aas_core_meta/__init__.py
aas_core_meta/marker.py
aas_core_meta/py.typed
aas_core_meta/v3rc1.py
aas_core_meta/v3rc2.py
aas_core_meta.egg-info/PKG-INFO
aas_core_meta.egg-info/SOURCES.txt
aas_core_meta.egg-info/dependency_links.txt
aas_core_meta.egg-info/requires.txt
aas_core_meta.egg-info/top_level.txt