Metadata-Version: 2.1
Name: aas-core-meta
Version: 2022.4.30a2
Summary: Provide meta-models for Asset Administration Shell information model.
Home-page: https://github.com/aas-core-works/aas-core-meta
Author: Nico Braunisch, Marko Ristin, Marcin Sadurski
Author-email: rist@zhaw.ch
License: License :: OSI Approved :: MIT License
Keywords: asset administration shell,design-by-contract,meta-model
Platform: UNKNOWN
Classifier: Development Status :: 3 - Alpha
Classifier: License :: OSI Approved :: MIT License
Classifier: Programming Language :: Python :: 3.8
Provides-Extra: dev
License-File: LICENSE
